{
  "id": "",
  "name": "",
  "font_family": "iconfont",
  "css_prefix_text": "icon-",
  "description": "",
  "glyphs": [
    {
      "icon_id": "1159902",
      "name": "音量",
      "font_class": "yinliang",
      "unicode": "e626",
      "unicode_decimal": 58918
    },
    {
      "icon_id": "1304892",
      "name": "右箭头",
      "font_class": "youjiantou",
      "unicode": "e624",
      "unicode_decimal": 58916
    },
    {
      "icon_id": "1488905",
      "name": "暂停",
      "font_class": "zanting",
      "unicode": "e60c",
      "unicode_decimal": 58892
    },
    {
      "icon_id": "1917158",
      "name": "播放",
      "font_class": "play",
      "unicode": "e80f",
      "unicode_decimal": 59407
    },
    {
      "icon_id": "2154282",
      "name": "循环播放_32",
      "font_class": "xunhuanbofang",
      "unicode": "e66c",
      "unicode_decimal": 58988
    },
    {
      "icon_id": "2154283",
      "name": "单曲循环_32",
      "font_class": "danquxunhuan",
      "unicode": "e66d",
      "unicode_decimal": 58989
    },
    {
      "icon_id": "3851361",
      "name": "列表",
      "font_class": "liebiao",
      "unicode": "e660",
      "unicode_decimal": 58976
    },
    {
      "icon_id": "9447889",
      "name": "暂停",
      "font_class": "zanting1",
      "unicode": "e668",
      "unicode_decimal": 58984
    },
    {
      "icon_id": "15919282",
      "name": "静音",
      "font_class": "jingyin",
      "unicode": "e655",
      "unicode_decimal": 58965
    },
    {
      "icon_id": "16364336",
      "name": "循环",
      "font_class": "xunhuan",
      "unicode": "e636",
      "unicode_decimal": 58934
    },
    {
      "icon_id": "16648567",
      "name": "上一首",
      "font_class": "shangyishou",
      "unicode": "e61e",
      "unicode_decimal": 58910
    },
    {
      "icon_id": "16648569",
      "name": "下一首",
      "font_class": "xiayishou",
      "unicode": "e61f",
      "unicode_decimal": 58911
    },
    {
      "icon_id": "18963668",
      "name": "随机播放",
      "font_class": "suijibofang",
      "unicode": "e6a0",
      "unicode_decimal": 59040
    },
    {
      "icon_id": "20587098",
      "name": "关闭",
      "font_class": "guanbi",
      "unicode": "e6be",
      "unicode_decimal": 59070
    },
    {
      "icon_id": "21151020",
      "name": "暂停",
      "font_class": "zantingtingzhi",
      "unicode": "e65a",
      "unicode_decimal": 58970
    },
    {
      "icon_id": "21181084",
      "name": "爱心",
      "font_class": "aixin",
      "unicode": "e61b",
      "unicode_decimal": 58907
    }
  ]
}
